[{
  "_id": {
    "$oid": "62feb60d9d973cb8ee31f33b"
  },
  "konveksi": "KBOGOR",
  "kodebarang": "D1000",
  "namabarang": "TOTEBAG ALICE",
  "hargamodal": "4000",
  "dailyprice": "4465",
  "linkproduk": "https://shopee.co.id/-LOKAL-DOMMO-D1000-Totebag-ALICE-BISA-COD-FYG-TAS-TOTE-BAG-TAS-WANITA-DARI-JAKARTA-i.135900627.2053489534?sp_atk=3466b1f5-6e9a-4ceb-984c-f4c2ec64c1d0",
  "hargaproduk": "4599",
  "pesaing": [
    {
      "namapesaing": "MORY MONY",
      "linkpesaing": "https://shopee.co.id/RR-TOTE-BAG-ALICE-MINI-i.154549401.7301389994?sp_atk=9fcd86ec-c897-4023-9e1c-c2588ad9cf06&xptdk=9fcd86ec-c897-4023-9e1c-c2588ad9cf06",
      "hargapesaing": "5000",
      "_id": {
        "$oid": "6305349ac99090d76511768a"
      }
    },
    {
      "namapesaing": "REYRESHY",
      "linkpesaing": "https://shopee.co.id/RR-TOTE-BAG-ALICE-MINI-i.154549401.7301389994?sp_atk=6770af19-466e-4abb-ae2c-ae6bbbf16bcb&xptdk=6770af19-466e-4abb-ae2c-ae6bbbf16bcb",
      "hargapesaing": "5000",
      "_id": {
        "$oid": "6305349ac99090d76511768b"
      }
    }
  ],
  "updatedAt": {
    "$date": {
      "$numberLong": "1661376472969"
    }
  },
  "__v": 0
},{
  "_id": {
    "$oid": "62fea8bd306246d109da6c27"
  },
  "konveksi": "KBOGOR",
  "kodebarang": "D1012",
  "namabarang": "TAS MINI PETAK",
  "hargamodal": "5000",
  "dailyprice": "5500",
  "linkproduk": "https://shopee.co.id/-LOKAL-DOMMO-D1012-Tas-Mini-Petak-Tas-Selempang-Tas-Tote-Bag-i.135900627.2060297469?sp_atk=383566d6-e402-4692-ac60-7f6852c55230",
  "hargaproduk": "5340",
  "pesaing": [
    {
      "namapesaing": "-",
      "linkpesaing": "-",
      "hargapesaing": "-"
    },
    {
      "namapesaing": "REYRESHY",
      "linkpesaing": "https://shopee.co.id/FYGALERY-FYG1140-Tas-Selempang-Perempuan-Slingbag-Polos-Fashion-Wanita-Sling-Bag-Korea-Murah-i.11184349.1104716811?sp_atk=e382bbe4-e24a-49e9-9325-725b8185f77d&xptdk=e382bbe4-e24a-49e9-9325-725b8185f77d",
      "hargapesaing": "6384"
    }
  ],
  "updatedAt": {
    "$date": {
      "$numberLong": "1660859917360"
    }
  },
  "__v": 0
},{
  "_id": {
    "$oid": "62feaa42306246d109da6c28"
  },
  "konveksi": "KBOGOR",
  "kodebarang": "D1020",
  "namabarang": "TAS NIA",
  "hargamodal": "11500",
  "dailyprice": "12500",
  "linkproduk": "https://shopee.co.id/-LOKAL-DOMMO-D1020-BISA-COD-BAYAR-DITEMPAT-TAS-FASHION-TAS-WANITA-Dari-Jakarta-MORYMONY-i.135900627.2060297501?sp_atk=dc3a2da2-a9d1-44b0-b3a8-facbe3e4dee1",
  "hargaproduk": "12500",
  "pesaing": [
    {
      "namapesaing": "MORY MONY",
      "linkpesaing": "https://shopee.co.id/MORYMONY-NIA-Tas-Selempang-Wanita-i.20287667.6400193845?sp_atk=26c3dac7-6a4e-47d8-b92a-0f9cd25b7654",
      "hargapesaing": "Habis"
    },
    {
      "namapesaing": "REYRESHY",
      "linkpesaing": "https://shopee.co.id/Tas-Nia-selempang-mini-rantai-motif-serat-kayu-i.14816430.5887017296?sp_atk=f653bc9a-f443-4e1a-ac0b-e240099ad695&xptdk=f653bc9a-f443-4e1a-ac0b-e240099ad695",
      "hargapesaing": "12500"
    }
  ],
  "updatedAt": {
    "$date": {
      "$numberLong": "1660859917360"
    }
  },
  "__v": 0
},{
  "_id": {
    "$oid": "62feaab4306246d109da6c29"
  },
  "konveksi": "KBOGOR",
  "kodebarang": "D1025",
  "namabarang": "HNM Tas Korea Clutch Sligbang",
  "hargamodal": "9000",
  "dailyprice": "9999",
  "linkproduk": "https://shopee.co.id/-LOKAL-DOMMO-D1025-BISA-COD-BAYAR-DITEMPAT-Tas-Korea-Clutch-Sligbang-Morymony-JKT-i.135900627.2304813663?sp_atk=55b8e17d-f824-4078-be07-79af79114554",
  "hargaproduk": "9999",
  "pesaing": [
    {
      "namapesaing": "-",
      "linkpesaing": "-",
      "hargapesaing": "-"
    },
    {
      "namapesaing": "-",
      "linkpesaing": "-",
      "hargapesaing": "-"
    }
  ],
  "updatedAt": {
    "$date": {
      "$numberLong": "1660859917360"
    }
  },
  "__v": 0
},{
  "_id": {
    "$oid": "62feab90306246d109da6c2a"
  },
  "konveksi": "KBOGOR",
  "kodebarang": "D1026",
  "namabarang": "ZANET ADA PEREKAT",
  "hargamodal": "4300",
  "dailyprice": "5500",
  "linkproduk": "https://shopee.co.id/-LOKAL-DOMMO-D1026-ZANET-ADA-RESLETING-Dari-JKT-Jakarta-BISA-COD-TAS-TOTE-BAG-WANITA-SLEMPANG-i.135900627.2312930347?sp_atk=ff28d140-0ee3-48cf-ac4f-7d97980de401",
  "hargaproduk": "5500",
  "pesaing": [
    {
      "namapesaing": "REYRESHY",
      "linkpesaing": "https://shopee.co.id/RR-ZANET-Tote-Bag-Wanita-i.154549401.3437832666?sp_atk=351f9a54-94a2-45e6-8361-6b85fa7d403b",
      "hargapesaing": "6500"
    },
    {
      "namapesaing": "-",
      "linkpesaing": "-",
      "hargapesaing": "-"
    }
  ],
  "updatedAt": {
    "$date": {
      "$numberLong": "1660859917360"
    }
  },
  "__v": 0
},{
  "_id": {
    "$oid": "62feac8f306246d109da6c2b"
  },
  "konveksi": "KBOGOR",
  "kodebarang": "D1026",
  "namabarang": "ZANET ADA RESLETING",
  "hargamodal": "5000",
  "dailyprice": "6000",
  "linkproduk": "https://shopee.co.id/-LOKAL-DOMMO-D1026-ZANET-ADA-RESLETING-Dari-JKT-Jakarta-BISA-COD-TAS-TOTE-BAG-WANITA-SLEMPANG-i.135900627.2312930347?sp_atk=ff28d140-0ee3-48cf-ac4f-7d97980de401",
  "hargaproduk": "6000",
  "pesaing": [
    {
      "namapesaing": "MORY MONY",
      "linkpesaing": "https://shopee.co.id/RR-ZANET-Tote-Bag-Wanita-Pakai-Resleting-i.154549401.3437832666?sp_atk=798bb02d-308c-4f65-a61b-0100b2296bd8&xptdk=798bb02d-308c-4f65-a61b-0100b2296bd8",
      "hargapesaing": "6000"
    },
    {
      "namapesaing": "REYRESHY",
      "linkpesaing": "https://shopee.co.id/RR-ZANET-Tote-Bag-Wanita-Pakai-Resleting-i.154549401.3437832666?sp_atk=da80397b-5491-4861-b532-464c14e0de6b&xptdk=da80397b-5491-4861-b532-464c14e0de6b",
      "hargapesaing": "6000"
    }
  ],
  "updatedAt": {
    "$date": {
      "$numberLong": "1660859917360"
    }
  },
  "__v": 0
}]